{
  "records": [
    {
      "date": "2026-02-26",
      "spx": 6900.39,
      "spx_h": 6947.25,
      "spx_l": 6859.73,
      "vix": 15.06
    },
    {
      "date": "2026-03-01",
      "spx": 6878.88,
      "spx_h": 6882.96,
      "spx_l": 6831.74,
      "vix": 19.86
    },
    {
      "date": "2026-03-02",
      "spx": 6878.88,
      "spx_h": 6882.96,
      "spx_l": 6831.74,
      "vix": 19.86
    },
    {
      "date": "2026-03-03",
      "spx": 6794.1,
      "spx_h": 6800.26,
      "spx_l": 6710.42,
      "vix": 24.49
    },
    {
      "date": "2026-03-04",
      "spx": 6877.86,
      "spx_h": 6880.38,
      "spx_l": 6811.64,
      "vix": 20.76
    },
    {
      "date": "2026-03-05",
      "spx": 6776.39,
      "spx_h": 6870.43,
      "spx_l": 6770.78,
      "vix": 24.89
    },
    {
      "date": "2026-03-06",
      "spx": 6758.86,
      "spx_h": 6773.42,
      "spx_l": 6711.56,
      "vix": 25.4
    },
    {
      "date": "2026-03-09",
      "spx": 6698.79,
      "spx_h": 6734.64,
      "spx_l": 6636.04,
      "vix": 27.76
    },
    {
      "date": "2026-03-10",
      "spx": 6833.43,
      "spx_h": 6845.08,
      "spx_l": 6759.74,
      "vix": 22.39
    },
    {
      "date": "2026-03-11",
      "spx": 6746.59,
      "spx_h": 6811.15,
      "spx_l": 6746.25,
      "vix": 24.77
    },
    {
      "date": "2026-03-12",
      "spx": 6703.67,
      "spx_h": 6740.88,
      "spx_l": 6680.1,
      "vix": 25.91
    },
    {
      "date": "2026-03-13",
      "spx": 6646.26,
      "spx_h": 6733.3,
      "spx_l": 6641.52,
      "vix": 27.05
    },
    {
      "date": "2026-03-16",
      "spx": 6706.07,
      "spx_h": 6722.87,
      "spx_l": 6674.37,
      "vix": 24.12
    },
    {
      "date": "2026-03-17",
      "spx": 6730.76,
      "spx_h": 6754.3,
      "spx_l": 6710.8,
      "vix": 22.23
    }
  ]
}